django_dramatiq_pg_adapter/admin.py
django_dramatiq_pg_adapter/app.py
django_dramatiq_pg_adapter/migrations/0001_initial.py
django_dramatiq_pg_adapter/migrations/__init__.py
django_dramatiq_pg_adapter/models.py
django_dramatiq_pg_adapter/utils.py
django_dramatiq_pg_adapter-1.0.0.dist-info/LICENSE
django_dramatiq_pg_adapter-1.0.0.dist-info/METADATA
django_dramatiq_pg_adapter-1.0.0.dist-info/WHEEL
django_dramatiq_pg_adapter-1.0.0.dist-info/RECORD
